texcli/__init__.py
texcli/cli.py
texcli/commands.py
texcli/experiment.py
texcli-0.0.9.dist-info/METADATA
texcli-0.0.9.dist-info/WHEEL
texcli-0.0.9.dist-info/entry_points.txt
texcli-0.0.9.dist-info/top_level.txt
texcli-0.0.9.dist-info/RECORD
