Metadata-Version: 2.1
Name: texcli
Version: 0.0.9
Summary: Convert TeX to images on the command line.
Home-page: https://github.com/maroba
Author: Matthias Baer
Author-email: matthias.r.baer@googlemail.com
License: None
Platform: ALL
Classifier: Operating System :: OS Independent
Classifier: Programming Language :: Python :: 3
Requires-Python: >=3.6
Requires-Dist: sphinx
Requires-Dist: Click
Requires-Dist: matplotlib
Requires-Dist: scikit-image
